Metadata-Version: 2.1
Name: libpythonpro-edna
Version: 0.2
Summary: Módulo para exemplificar construção de projetos Python no curso PyTools
Home-page: https://github.com/ednai/libpythonpro
Author: Edna Silva
Author-email: edkujo@gmail.com
Classifier: Development Status :: 2 - Pre-Alpha
Classifier: Environment :: Console
Classifier: Intended Audience :: Developers
Classifier: License :: OSI Approved :: GNU Affero General Public License v3 or later (AGPLv3+)
Classifier: Operating System :: OS Independent
Classifier: Programming Language :: Python
Classifier: Programming Language :: Python :: 3.6
Classifier: Framework :: Pytest
License-File: LICENSE
